{"cameraMode":{"drawMode":0,"name":"Shaded","section":"Shading Mode"},"sceneLighting":true,"audioPlay":false,"sceneViewState":{"m_AlwaysRefresh":false,"showFog":true,"showSkybox":true,"showFlares":true,"showImageEffects":true,"showParticleSystems":true,"showVisualEffectGraphs":true,"m_FxEnabled":true},"in2DMode":false,"pivot":{"x":-9.967435836791993,"y":24.55195426940918,"z":46.1628532409668},"rotation":{"x":0.013297827914357186,"y":0.9723805785179138,"z":-0.2259434461593628,"w":0.05724826082587242},"size":0.6928974390029907,"orthographic":false}